{
  "schemaVersion": 1,
  "app": {
    "name": "pathguard",
    "version": "0.1.0",
    "programFile": "../outside/Escape.lpr"
  },
  "commands": [
    {
      "name": "greet",
      "description": "Say hello",
      "parent": "",
      "parameters": [
        {
          "kind": "string",
          "short": "-n",
          "long": "--name",
          "description": "Name to greet",
          "required": false,
          "default": "World",
          "allowedValues": ""
        }
      ]
    }
  ]
}
